{
  "greeting": "👋 Hey",
  "name": "Amit !",
  "greetingText": "I hope u r doing well",
  "imagePath": "https://maityamit.github.io/maityamit-portfolio/assets/images/hero.png",
  "text1": "Today's your special day !",
  "text0": "It's your Birthday !!!",
  "textInChatBox": "Wish u Happy birthday 🎂 !! 🎉 Yeee! Many many happy blah...",
  "sendButtonLabel": "Send",
  "text2": "That's what I was going to do.",
  "text3": "But then I stopped & realised",
  "text4": "I can do something very",
  "text4Adjective": "Unique",
  "text5Entry": "Because, I'm a Developer ;)",
  "smiley": ":)",
  "bigTextPart1": "s",
  "bigTextPart2": "o",
  "text5Content": "Here it is ",
  "wishHeading": "Happy Birthday !",
  "wishText": "May the js.prototypes always be with you! ;) I hope you have a fabulous birthday today and all your wishes come true!",
  "outroText": "Okay, That was it ! Enjoy your day !",
  "replayText": "rewatch",
  "outroSmiley": ":)"
}